suchak/__init__.py
suchak/atr.py
suchak/deque.py
suchak/ema.py
suchak/fibo.py
suchak/jitclass.py
suchak/macd.py
suchak/rma.py
suchak/rsi.py
suchak/sma.py
suchak/supertrend.py
suchak/tr.py
suchak/vec.py
suchak/window.py
suchak/zig_zag_pivots.py
suchak-0.3.0.dist-info/METADATA
suchak-0.3.0.dist-info/WHEEL
suchak-0.3.0.dist-info/top_level.txt
suchak-0.3.0.dist-info/RECORD
